{
  "project_info": {
    "project_number": "720477975912",
    "project_id": "chatapplication-b37e1",
    "storage_bucket": "chatapplication-b37e1.appspot.com"
  },
  "client": [
    {
      "client_info": {
        "mobilesdk_app_id": "1:720477975912:android:b4765ef5de4ec0e99d92dd",
        "android_client_info": {
          "package_name": "com.example.chatapplication"
        }
      },
      "oauth_client": [
        {
          "client_id": "720477975912-q63qen8obulv6kqsmu9spid5tep2fh35.apps.googleusercontent.com",
          "client_type": 3
        }
      ],
      "api_key": [
        {
          "current_key": "AIzaSyAZ83qLoLTMq11_BCD4imerVd05iKDfnGs"
        }
      ],
      "services": {
        "appinvite_service": {
          "other_platform_oauth_client": [
            {
              "client_id": "720477975912-q63qen8obulv6kqsmu9spid5tep2fh35.apps.googleusercontent.com",
              "client_type": 3
            }
          ]
        }
      }
    }
  ],
  "configuration_version": "1"
}